knitkit/__init__.py
knitkit/main.py
knitkit/version.py
knitkit/assets/Main.scala
knitkit/assets/build.sc
knitkit/assets/default.yaml
knitkit/assets/project.mk
knitkit/jars/knitkit.jar
knitkit-0.3.dist-info/LICENSE
knitkit-0.3.dist-info/METADATA
knitkit-0.3.dist-info/WHEEL
knitkit-0.3.dist-info/entry_points.txt
knitkit-0.3.dist-info/top_level.txt
knitkit-0.3.dist-info/RECORD
